Metadata-Version: 1.0
Name: section
Version: 1.0
Summary: hottopic knowledge section 
Home-page: UNKNOWN
Author: Yan Xing
Author-email: UNKNOWN
License: UNKNOWN
Platform: UNKNOWN
